divio_cli/__init__.py
divio_cli/api_requests.py
divio_cli/check_system.py
divio_cli/cli.py
divio_cli/client.py
divio_cli/cloud.py
divio_cli/config.py
divio_cli/excepthook.py
divio_cli/exceptions.py
divio_cli/messages.py
divio_cli/settings.py
divio_cli/utils.py
divio_cli/version.py
divio_cli/widgets.py
divio_cli/wizards.py
divio_cli/wizards_utils.py
divio_cli/domain_models/__init__.py
divio_cli/domain_models/app_template.py
divio_cli/localdev/__init__.py
divio_cli/localdev/backups.py
divio_cli/localdev/main.py
divio_cli/localdev/push.py
divio_cli/localdev/utils.py
divio_cli/test/__init__.py
divio_cli/test/conftest.py
divio_cli/test/test_commands.py
divio_cli/test/test_deployments_commands.py
divio_cli/test/test_environment_variables_commands.py
divio_cli/test/test_exceptions.py
divio_cli/test/test_localdev_backups.py
divio_cli/test/test_localdev_push.py
divio_cli/test/test_localdev_utils.py
divio_cli/test/test_project_settings.py
divio_cli/upload/__init__.py
divio_cli/upload/addon.py
divio_cli/upload/common.py
divio_cli/validators/__init__.py
divio_cli/validators/addon.py
divio_cli/validators/common.py
divio_cli-4.0.5.dist-info/licenses/LICENSE.txt
divio_cli-4.0.5.dist-info/METADATA
divio_cli-4.0.5.dist-info/WHEEL
divio_cli-4.0.5.dist-info/entry_points.txt
divio_cli-4.0.5.dist-info/top_level.txt
divio_cli-4.0.5.dist-info/RECORD
