Metadata-Version: 2.4
Name: divio-cli
Version: 4.0.5
Summary: The command-line client for the Divio Cloud
Author-email: Divio AG <info@divio.com>
License: Copyright (c) 2015, Divio AG
Project-URL: homepage, https://docs.divio.com/en/latest/how-to/local-cli/
Platform: any
Classifier: Development Status :: 4 - Beta
Classifier: Environment :: Console
Classifier: Intended Audience :: Developers
Classifier: License :: OSI Approved :: BSD License
Classifier: Operating System :: OS Independent
Classifier: Programming Language :: Python
Classifier: Programming Language :: Python :: 3
Classifier: Programming Language :: Python :: 3.7
Classifier: Programming Language :: Python :: 3.8
Classifier: Programming Language :: Python :: 3.9
Classifier: Programming Language :: Python :: 3.10
Classifier: Programming Language :: Python :: 3.11
Classifier: Topic :: Software Development
Requires-Python: >=3.7
License-File: LICENSE.txt
Requires-Dist: attrs
Requires-Dist: azure-storage-blob
Requires-Dist: boto3
Requires-Dist: click>=7.0
Requires-Dist: click_aliases
Requires-Dist: colorama; sys_platform == "win32"
Requires-Dist: giturl
Requires-Dist: inquirer
Requires-Dist: packaging
Requires-Dist: pyaml
Requires-Dist: python-dateutil
Requires-Dist: requests
Requires-Dist: sentry-sdk
Requires-Dist: tabulate>=0.8.10
Requires-Dist: simple-logging-setup
Requires-Dist: urllib3
Requires-Dist: pyreadline3; platform_system == "Windows"
Provides-Extra: dev
Requires-Dist: tox; extra == "dev"
Requires-Dist: build; extra == "dev"
Provides-Extra: test
Requires-Dist: pytest; extra == "test"
Requires-Dist: pytest-cov; extra == "test"
Dynamic: license-file
